csig/__init__.py
csig/sigv4.py
csig-0.1.3.dist-info/LICENSE
csig-0.1.3.dist-info/METADATA
csig-0.1.3.dist-info/WHEEL
csig-0.1.3.dist-info/top_level.txt
csig-0.1.3.dist-info/RECORD
