Metadata-Version: 2.1
Name: csig
Version: 0.1.3
Summary: Implementation of AWS Signature Version 4
Requires-Python: >=3.8
License-File: LICENSE
